LICENSE
MANIFEST.in
README.rst
setup.py
django_pagebase.egg-info/PKG-INFO
django_pagebase.egg-info/SOURCES.txt
django_pagebase.egg-info/dependency_links.txt
django_pagebase.egg-info/not-zip-safe
django_pagebase.egg-info/requires.txt
django_pagebase.egg-info/top_level.txt
pagebase/__init__.py
pagebase/admin.py
pagebase/helpers.py
pagebase/middleware.py
pagebase/views.py
pagebase/locale/sv/LC_MESSAGES/django.mo
pagebase/locale/sv/LC_MESSAGES/django.po
pagebase/models/__init__.py
pagebase/models/base.py
pagebase/models/fields.py
pagebase/templates/pagebase/admin/change_list.html
pagebase/templates/pagebase/admin/change_list_results.html
pagebase/templatetags/__init__.py
pagebase/templatetags/pagebase_admin_list.py