Metadata-Version: 1.0
Name: django-pagebase
Version: 0.4.1
Summary: Pages for Django
Home-page: https://github.com/aino/django-pagebase
Author: Mikko Hellsing
Author-email: mikko@aino.se
License: BSD
Platform: any
Classifier: Development Status :: 2 - Pre-Alpha
Classifier: Environment :: Web Environment
Classifier: Intended Audience :: Developers
Classifier: License :: OSI Approved :: BSD License
Classifier: Operating System :: OS Independent
Classifier: Programming Language :: Python
Classifier: Topic :: Internet :: WWW/HTTP :: Dynamic Content
Classifier: Framework :: Django
